amsdal_agent/__about__.py
amsdal_agent/__init__.py
amsdal_agent/constants.py
amsdal_agent/cli/__init__.py
amsdal_agent/cli/supervisor.py
amsdal_agent/processes/__init__.py
amsdal_agent/processes/server_process.py
amsdal_agent/processes/worker_process.py
amsdal_agent/queues/__init__.py
amsdal_agent/queues/base.py
amsdal_agent/queues/manager.py
amsdal_agent/queues/persistent_queue.py
amsdal_agent/queues/redis_queue.py
amsdal_agent/services/__init__.py
amsdal_agent/services/options.py
amsdal_agent/services/server.py
amsdal_agent/services/worker.py
amsdal_agent-0.0.7.dist-info/METADATA
amsdal_agent-0.0.7.dist-info/WHEEL
amsdal_agent-0.0.7.dist-info/entry_points.txt
amsdal_agent-0.0.7.dist-info/licenses/LICENSE.txt
amsdal_agent-0.0.7.dist-info/RECORD
