Metadata-Version: 2.1
Name: amsdal_agent
Version: 0.0.7
Summary: Agent to connect AMSDAL SDK with server
Project-URL: Documentation, https://github.com/amsdal/amsdal_integrations/#readme
Project-URL: Issues, https://github.com/amsdal/amsdal_integrations/issues
Project-URL: Source, https://github.com/amsdal/amsdal_integrations/tree/main/tools/amsdal-agent
License: AMSDAL End User License Agreement
License-File: LICENSE.txt
Classifier: Development Status :: 4 - Beta
Classifier: Programming Language :: Python
Classifier: Programming Language :: Python :: 3.7
Classifier: Programming Language :: Python :: 3.8
Classifier: Programming Language :: Python :: 3.9
Classifier: Programming Language :: Python :: 3.10
Classifier: Programming Language :: Python :: 3.11
Classifier: Programming Language :: Python :: Implementation :: CPython
Classifier: Programming Language :: Python :: Implementation :: PyPy
Requires-Python: >=3.7
Requires-Dist: httpx~=0.23
Requires-Dist: rich~=13.7
Provides-Extra: redis
Requires-Dist: redis==5.0.1; extra == 'redis'
